action_items_local/__init__.py
action_items_local/action_items_local.py
action_items_local/action_items_local_constants.py
action_items_local-0.0.14.dist-info/METADATA
action_items_local-0.0.14.dist-info/WHEEL
action_items_local-0.0.14.dist-info/top_level.txt
action_items_local-0.0.14.dist-info/RECORD
