Metadata-Version: 2.1
Name: action-items-local
Version: 0.0.14
Summary: PyPI Package for Circles action-items-local Python
Home-page: https://github.com/circles-zone/action-item-local-python-package
Author: Circles
Author-email: info@circlez.ai
Classifier: Programming Language :: Python :: 3
Classifier: License :: Other/Proprietary License
Classifier: Operating System :: OS Independent
Requires-Dist: pytest >=7.4.0
Requires-Dist: logzio-python-handler >=4.1.0
Requires-Dist: user-context-remote >=0.0.58
Requires-Dist: python-sdk-remote >=0.0.27
Requires-Dist: database-mysql-local >=0.0.221
Requires-Dist: logger-local >=0.0.108
Requires-Dist: language-remote >=0.0.15
